meshify.py
meshify-0.1.3.dist-info/DESCRIPTION.rst
meshify-0.1.3.dist-info/METADATA
meshify-0.1.3.dist-info/RECORD
meshify-0.1.3.dist-info/WHEEL
meshify-0.1.3.dist-info/entry_points.txt
meshify-0.1.3.dist-info/metadata.json
meshify-0.1.3.dist-info/top_level.txt
