Metadata-Version: 2.0
Name: meshify
Version: 0.1.3
Summary: Package to interact with the Meshify API
Home-page: https://patrickjmcd.github.io/Meshify-Python-API/
Author: Patrick McDonagh
Author-email: patrickjmcd@gmail.com
License: Apache 2.0
Project-URL: Source, https://github.com/patrickjmcd/Meshify-Python-API/
Project-URL: Tracker, https://github.com/patrickjmcd/Meshify-Python-API/issues
Keywords: meshify api cloud
Platform: UNKNOWN
Classifier: Development Status :: 3 - Alpha
Classifier: Intended Audience :: Developers
Classifier: Topic :: Software Development :: Build Tools
Classifier: License :: OSI Approved :: Apache Software License
Classifier: Programming Language :: Python :: 2
Classifier: Programming Language :: Python :: 2.6
Classifier: Programming Language :: Python :: 2.7
Classifier: Programming Language :: Python :: 3
Classifier: Programming Language :: Python :: 3.2
Classifier: Programming Language :: Python :: 3.3
Classifier: Programming Language :: Python :: 3.4
Classifier: Programming Language :: Python :: 3.5
Classifier: Programming Language :: Python :: 3.6
Requires-Dist: Click
Requires-Dist: requests
